<conditions>
<condition name="N/A"></condition>
<condition name="Selkeää"></condition>
<condition name="Osin selkeää"></condition>
<condition name="Lumisadetta"></condition>
<condition name="Melko pilvistä"></condition>
<condition name="Pilvistä"></condition>
<condition name="Sadetta"></condition>
<condition name="Melko pilvistä, ukkoskuuroja"></condition>
<condition name="Vaihtelevaa pilvisyyttä"></condition>
<condition name="Melko pilvistä"></condition>
<condition name="Melko pilvistä"></condition>
<condition name="Osin pilvistä, sadekuuroja"></condition>
<condition name="Lumi"></condition>
<condition name="Sumua"></condition>
<condition name="Utua"></condition>
</conditions>

